pact_langchain/__init__.py
pact_langchain/client.py
pact_langchain/memory.py
pact_langchain/version.py
pact_langchain-0.1.0.dist-info/licenses/LICENSE
tests/__init__.py
tests/test_memory.py
pact_langchain-0.1.0.dist-info/METADATA
pact_langchain-0.1.0.dist-info/WHEEL
pact_langchain-0.1.0.dist-info/top_level.txt
pact_langchain-0.1.0.dist-info/RECORD
