Metadata-Version: 2.4
Name: pact-langchain
Version: 0.1.0
Summary: LangChain memory with emotional intelligence by NeurobloomAI
Home-page: https://github.com/neurobloomai/pact-hx
Author: NeurobloomAI
Author-email: NeurobloomAI <hello@neurobloom.ai>
License: MIT
Project-URL: Homepage, https://neurobloom.ai
Project-URL: Documentation, https://docs.neurobloom.ai/pact/langchain
Project-URL: Repository, https://github.com/neurobloomai/pact-hx
Project-URL: Issues, https://github.com/neurobloomai/pact-hx/issues
Keywords: langchain,memory,ai,llm,emotional-intelligence,pact,neurobloom
Requires-Python: >=3.8
License-File: LICENSE
Requires-Dist: langchain>=0.1.0
Requires-Dist: langchain-core>=0.1.0
Requires-Dist: requests>=2.28.0
Requires-Dist: pydantic>=2.0.0
Provides-Extra: dev
Requires-Dist: pytest>=7.0.0; extra == "dev"
Requires-Dist: pytest-asyncio>=0.21.0; extra == "dev"
Requires-Dist: pytest-cov>=4.0.0; extra == "dev"
Requires-Dist: black>=23.0.0; extra == "dev"
Requires-Dist: mypy>=1.0.0; extra == "dev"
Requires-Dist: ruff>=0.1.0; extra == "dev"
Dynamic: author
Dynamic: home-page
Dynamic: license-file
Dynamic: requires-python
